LICENSE
MANIFEST.in
README.md
scrape_facebook.py
setup.cfg
setup.py
scrape_facebook.egg-info/PKG-INFO
scrape_facebook.egg-info/SOURCES.txt
scrape_facebook.egg-info/dependency_links.txt
scrape_facebook.egg-info/requires.txt
scrape_facebook.egg-info/top_level.txt