Metadata-Version: 2.1
Name: scrape-facebook
Version: 0.1.7
Summary: Scrape Facebook public pages without an API key.
Home-page: https://github.com/amitkadivar/scrapefacebook
Author: Amit Kadivar
Author-email: amit.kadivar1@gmail.com
License: MIT
Platform: UNKNOWN
Classifier: License :: OSI Approved :: MIT License
Classifier: Programming Language :: Python
Classifier: Programming Language :: Python :: 3.6
Classifier: Programming Language :: Python :: Implementation :: CPython
Classifier: Programming Language :: Python :: Implementation :: PyPy
Requires-Python: >=3.6.0
